adaptive_stratification/__init__.py
adaptive_stratification/stratification.py
adaptive_stratification/stratum.py
adaptive_stratification-1.0.1.dist-info/LICENSE
adaptive_stratification-1.0.1.dist-info/METADATA
adaptive_stratification-1.0.1.dist-info/WHEEL
adaptive_stratification-1.0.1.dist-info/top_level.txt
adaptive_stratification-1.0.1.dist-info/RECORD
