Metadata-Version: 2.1
Name: adaptive-stratification
Version: 1.0.1
Summary: Adaptive Stratification library
Home-page: https://github.com/SKrumscheid/ADSS
License: MIT License
Platform: any
Classifier: Programming Language :: Python :: 3
Classifier: License :: OSI Approved :: MIT License
Classifier: Operating System :: OS Independent
Classifier: Development Status :: 4 - Beta
Requires-Python: >=3.8
License-File: LICENSE
Requires-Dist: scipy
Requires-Dist: numpy
